{
	"configurations" : 
	[
		{
			"directories" : 
			[
				{
					"build" : ".",
					"jsonFile" : "directory-.-Debug-d0094a50bb2071803777.json",
					"minimumCMakeVersion" : 
					{
						"string" : "3.27"
					},
					"projectIndex" : 0,
					"source" : ".",
					"targetIndexes" : 
					[
						0
					]
				}
			],
			"name" : "Debug",
			"projects" : 
			[
				{
					"directoryIndexes" : 
					[
						0
					],
					"name" : "opencv2",
					"targetIndexes" : 
					[
						0
					]
				}
			],
			"targets" : 
			[
				{
					"directoryIndex" : 0,
					"id" : "opencv2::@6890427a1f51a3e7e1df",
					"jsonFile" : "target-opencv2-Debug-3d76efc4897c5c0b3412.json",
					"name" : "opencv2",
					"projectIndex" : 0
				}
			]
		}
	],
	"kind" : "codemodel",
	"paths" : 
	{
		"build" : "D:/xrsspace/app/opencv2/cmake-build-debug",
		"source" : "D:/xrsspace/app/opencv2"
	},
	"version" : 
	{
		"major" : 2,
		"minor" : 6
	}
}
